django_cute_status/__init__.py
django_cute_status/apps.py
django_cute_status/middleware.py
django_cute_status/conf/__init__.py
django_cute_status/conf/defaults.py
django_cute_status/templates/django_cute_status/base.html
django_cute_status-2.0.0.dist-info/METADATA
django_cute_status-2.0.0.dist-info/WHEEL
django_cute_status-2.0.0.dist-info/licenses/LICENSE
django_cute_status-2.0.0.dist-info/RECORD
