Metadata-Version: 2.4
Name: django-cute-status
Version: 2.0.0
Summary: A django application to display cute animal pictures based on HTTP status codes.
Project-URL: Documentation, https://github.com/abhiabhi94/django-cute-status
Project-URL: Source Code, https://github.com/abhiabhi94/django-cute-status
Project-URL: Homepage, https://github.com/abhiabhi94/django-cute-status
Author: Abhyudai
License-Expression: MIT
License-File: LICENSE
Keywords: django,dogs,status,status-codes
Classifier: Environment :: Web Environment
Classifier: Framework :: Django
Classifier: Framework :: Django :: 4.2
Classifier: Framework :: Django :: 5.0
Classifier: Framework :: Django :: 5.1
Classifier: Framework :: Django :: 5.2
Classifier: Intended Audience :: Developers
Classifier: Operating System :: OS Independent
Classifier: Programming Language :: Python
Classifier: Programming Language :: Python :: 3.10
Classifier: Programming Language :: Python :: 3.11
Classifier: Programming Language :: Python :: 3.12
Classifier: Programming Language :: Python :: 3.13
Classifier: Topic :: Internet :: WWW/HTTP
Classifier: Topic :: Internet :: WWW/HTTP :: Dynamic Content
Requires-Python: >=3.10
Requires-Dist: django
Provides-Extra: dev
Requires-Dist: coverage; extra == 'dev'
Requires-Dist: pre-commit; extra == 'dev'
Requires-Dist: pytest-django; extra == 'dev'
Requires-Dist: pytest-randomly; extra == 'dev'
